MANIFEST.in
README.md
VERSION
setup.py
docs/DeviceImageManagement.md
docs/EventsMetrics.md
docs/Examples.md
docs/ManagingDevice.md
docs/RpcGuidelines.md
docs/images/device_image_management.drawio
docs/images/device_image_management.png
docs/images/device_image_management_fsm.drawio
docs/images/device_image_management_fsm.png
docs/images/events_metrics.drawio
docs/images/events_metrics.png
docs/images/managing_device.drawio
docs/images/managing_device.png
protos/dmi/commons.proto
protos/dmi/hw.proto
protos/dmi/hw_events_mgmt_service.proto
protos/dmi/hw_management_service.proto
protos/dmi/hw_metrics_mgmt_service.proto
protos/dmi/sw_image.proto
protos/dmi/sw_management_service.proto
python/device_management_interface.egg-info/PKG-INFO
python/device_management_interface.egg-info/SOURCES.txt
python/device_management_interface.egg-info/dependency_links.txt
python/device_management_interface.egg-info/requires.txt
python/device_management_interface.egg-info/top_level.txt
python/dmi/__init__.py
python/dmi/commons_pb2.py
python/dmi/commons_pb2_grpc.py
python/dmi/hw_events_mgmt_service_pb2.py
python/dmi/hw_events_mgmt_service_pb2_grpc.py
python/dmi/hw_management_service_pb2.py
python/dmi/hw_management_service_pb2_grpc.py
python/dmi/hw_metrics_mgmt_service_pb2.py
python/dmi/hw_metrics_mgmt_service_pb2_grpc.py
python/dmi/hw_pb2.py
python/dmi/hw_pb2_grpc.py
python/dmi/sw_image_pb2.py
python/dmi/sw_image_pb2_grpc.py
python/dmi/sw_management_service_pb2.py
python/dmi/sw_management_service_pb2_grpc.py