Metadata-Version: 1.1
Name: device-management-interface
Version: 1.18.0
Summary: Protobuf interface definitions
Home-page: https://gerrit.opencord.org/plugins/gitiles/device-management-interface
Author: VOLTHA project
Author-email: voltha-dev@opencord.org
License: Apache Software License
Keywords: protobuf device-management-interface voltha
Platform: UNKNOWN
Classifier: Development Status :: 5 - Production/Stable
Classifier: Intended Audience :: Developers
Classifier: License :: OSI Approved :: Apache Software License
Classifier: Programming Language :: Python :: 3.6
